testiq/__init__.py
testiq/analysis.py
testiq/analyzer.py
testiq/cicd.py
testiq/cli.py
testiq/config.py
testiq/coverage_converter.py
testiq/examples/README.md
testiq/examples/ai-generated-tests/README.md
testiq/examples/ai-generated-tests/ai-test-report.html
testiq/examples/ai-generated-tests/calculator.py
testiq/examples/bash/quick_test.sh
testiq/examples/cicd/Jenkinsfile
testiq/examples/cicd/github-actions.yml
testiq/examples/cicd/gitlab-ci.yml
testiq/examples/python/manual_test.py
testiq/examples/python/pytest_plugin_example.py
testiq/exceptions.py
testiq/logging_config.py
testiq/performance.py
testiq/plugins.py
testiq/pytest_plugin.py
testiq/reporting.py
testiq/security.py
testiq/source_reader.py
testiq-0.2.2.dist-info/WHEEL
testiq-0.2.2.dist-info/entry_points.txt
testiq-0.2.2.dist-info/METADATA
testiq-0.2.2.dist-info/RECORD
