Metadata-Version: 2.3
Name: testiq
Version: 0.2.2
Summary: TestIQ - Intelligent test analysis for finding duplicate and redundant tests using coverage analysis
Keywords: testing,test-automation,coverage,duplicate-detection,test-quality,ci-cd
Author: Kiran K Kotari
Author-email: Kiran K Kotari <kirankotari@live.com>
Classifier: Development Status :: 4 - Beta
Classifier: Intended Audience :: Developers
Classifier: Topic :: Software Development :: Testing
Classifier: Topic :: Software Development :: Quality Assurance
Classifier: License :: OSI Approved :: MIT License
Classifier: Programming Language :: Python :: 3
Classifier: Programming Language :: Python :: 3.9
Classifier: Programming Language :: Python :: 3.10
Classifier: Programming Language :: Python :: 3.11
Classifier: Programming Language :: Python :: 3.12
Requires-Dist: click>=8.1.7
Requires-Dist: coverage>=7.4.0
Requires-Dist: rich>=13.7.0
Requires-Dist: pyyaml>=6.0.1
Requires-Dist: tomli>=2.0.1 ; python_full_version < '3.11'
Requires-Dist: pytest>=7.4.0
Requires-Dist: pytest>=7.4.0 ; extra == 'dev'
Requires-Dist: pytest-cov>=4.1.0 ; extra == 'dev'
Requires-Dist: ruff>=0.1.0 ; extra == 'dev'
Requires-Dist: black>=23.0.0 ; extra == 'dev'
Requires-Dist: mypy>=1.7.0 ; extra == 'dev'
Requires-Dist: types-click>=7.1.0 ; extra == 'dev'
Requires-Dist: types-pyyaml>=6.0.0 ; extra == 'dev'
Requires-Python: >=3.9
Project-URL: Homepage, https://github.com/testiq-dev/testiq
Project-URL: Documentation, https://github.com/testiq-dev/testiq/tree/main/docs
Project-URL: Repository, https://github.com/testiq-dev/testiq
Project-URL: Issues, https://github.com/testiq-dev/testiq/issues
Provides-Extra: dev
